ramby/__init__.py
ramby/ramby.py
ramby-0.0.5.dist-info/LICENSE
ramby-0.0.5.dist-info/METADATA
ramby-0.0.5.dist-info/WHEEL
ramby-0.0.5.dist-info/top_level.txt
ramby-0.0.5.dist-info/RECORD
