Metadata-Version: 2.1
Name: ramby
Version: 0.0.5
Summary: Ramby is a simple way to setup a webscraper
Home-page: https://github.com/keosariel/ramby
Author: keosariel
Author-email: kennethgabriel78@gmail.com
License: MIT
Keywords: python,crawler,scraper,bs4,beautifulsoup
Platform: UNKNOWN
Classifier: Development Status :: 1 - Planning
Classifier: Intended Audience :: Developers
Classifier: Programming Language :: Python :: 3
Classifier: Operating System :: Unix
Classifier: Operating System :: MacOS :: MacOS X
Classifier: Operating System :: Microsoft :: Windows
License-File: LICENSE
Requires-Dist: beautifulsoup4 (==4.11.1)
Requires-Dist: bs4 (==0.0.1)
Requires-Dist: certifi (==2022.6.15)
Requires-Dist: charset-normalizer (==2.1.0)
Requires-Dist: filelock (==3.7.1)
Requires-Dist: idna (==3.3)
Requires-Dist: MarkupSafe (==2.1.1)
Requires-Dist: PyYAML (==6.0)
Requires-Dist: requests (==2.28.1)
Requires-Dist: requests-file (==1.5.1)
Requires-Dist: six (==1.16.0)
Requires-Dist: soupsieve (==2.3.2.post1)
Requires-Dist: urllib3 (==1.26.11)
Requires-Dist: Werkzeug (==2.1.2)
